collections_extended/__init__.py
collections_extended/_util.py
collections_extended/_version.py
collections_extended/bags.py
collections_extended/bijection.py
collections_extended/indexed_dict.py
collections_extended/range_map.py
collections_extended/sentinel.py
collections_extended/setlists.py
collections_extended-2.0.1.dist-info/LICENSE
collections_extended-2.0.1.dist-info/WHEEL
collections_extended-2.0.1.dist-info/METADATA
collections_extended-2.0.1.dist-info/RECORD
