Metadata-Version: 2.1
Name: collections-extended
Version: 2.0.1
Summary: Extra Python Collections - bags (multisets) and setlists (ordered sets)
Home-page: https://github.com/mlenzen/collections-extended
License: Apache-2.0
Keywords: collections,bag,multiset,ordered set,unique list
Author: Michael Lenzen
Author-email: m.lenzen@gmail.com
Requires-Python: >=3.6,<4.0
Classifier: Development Status :: 5 - Production/Stable
Classifier: Intended Audience :: Developers
Classifier: License :: OSI Approved :: Apache Software License
Classifier: Operating System :: OS Independent
Classifier: Programming Language :: Python
Classifier: Programming Language :: Python :: 3
Classifier: Programming Language :: Python :: 3.10
Classifier: Programming Language :: Python :: 3.6
Classifier: Programming Language :: Python :: 3.7
Classifier: Programming Language :: Python :: 3.8
Classifier: Programming Language :: Python :: 3.9
Classifier: Programming Language :: Python :: Implementation :: PyPy
Classifier: Topic :: Software Development
Classifier: Topic :: Software Development :: Libraries
Classifier: Topic :: Software Development :: Libraries :: Python Modules
Provides-Extra: docs
Provides-Extra: testing
Project-URL: Documentation, https://collections-extended.lenzm.net
Project-URL: Repository, https://github.com/mlenzen/collections-extended
